outhouse/__init__.py
outhouse-0.1.0.dist-info/METADATA
outhouse-0.1.0.dist-info/RECORD
outhouse-0.1.0.dist-info/WHEEL
outhouse-0.1.0.dist-info/top_level.txt
